pg_save/__init__.py
pg_save/__main__.py
pg_save/cli/__init__.py
pg_save/cli/describe_table.py
pg_save/cli/group.py
pg_save/cli/interactive.py
pg_save/cli/list_tables.py
pg_save/cli/query.py
pg_save/cli/select_table.py
pg_save/database_description/__init__.py
pg_save/database_description/table_info.py
pg_save/database_description/tables_list.py
pg_save/dtos/__init__.py
pg_save/dtos/database.py
pg_save/exceptions/__init__.py
pg_save/exceptions/db_connect.py
pg_save/exceptions/table_not_fonud.py
pg_save/exceptions/unsafe_expression.py
pg_save/export/__init__.py
pg_save/export/csv.py
pg_save/export/default_crs.py
pg_save/export/excel.py
pg_save/export/geojson.py
pg_save/export/json.py
pg_save/export/united.py
pg_save/querying/__init__.py
pg_save/querying/query.py
pg_save/querying/table.py
pg_save/utils/__init__.py
pg_save/utils/dotenv.py
pg_save/utils/interactive.py
pg_save/utils/np_encoder.py
pg_save/utils/pd.py
pg_save/utils/print.py
pg_save-0.3.2.dist-info/LICENSE
pg_save-0.3.2.dist-info/METADATA
pg_save-0.3.2.dist-info/WHEEL
pg_save-0.3.2.dist-info/entry_points.txt
pg_save-0.3.2.dist-info/RECORD
