Metadata-Version: 2.1
Name: pg-save
Version: 0.3.2
Summary: An utility to export Postgres table data to a various formats without having GeoPandas as a requirement
Home-page: https://github.com/kanootoko/pg-save
License: MIT
Author: Aleksei Sokol
Author-email: kanootoko@gmail.com
Requires-Python: >=3.9,<4.0
Classifier: License :: OSI Approved :: MIT License
Classifier: Operating System :: OS Independent
Classifier: Programming Language :: Python :: 3
Classifier: Programming Language :: Python :: 3.9
Classifier: Programming Language :: Python :: 3.10
Classifier: Programming Language :: Python :: 3.11
Classifier: Programming Language :: Python :: 3.12
Classifier: Programming Language :: Python :: 3.13
Requires-Dist: click (>=8.1.6,<9.0.0)
Requires-Dist: loguru (>=0.7.0,<0.8.0)
Requires-Dist: numpy (>=1.25.1,<2.0.0)
Requires-Dist: pandas (>=2.0.3,<3.0.0)
Requires-Dist: psycopg2 (>=2.9.6,<3.0.0)
Requires-Dist: pyxlsx (>=1.1.3,<2.0.0)
Project-URL: Bug Tracker, https://github.com/kanootoko/pg-save/issues
Project-URL: Repository, https://github.com/kanootoko/pg-save
